sanskrit_data/__init__.py
sanskrit_data/collection_helper.py
sanskrit_data/file_helper.py
sanskrit_data/toml_helper.py
sanskrit_data/db/__init__.py
sanskrit_data/db/in_memory.py
sanskrit_data/db/interfaces/__init__.py
sanskrit_data/db/interfaces/ullekhanam_db.py
sanskrit_data/db/interfaces/users_db.py
sanskrit_data/schema/__init__.py
sanskrit_data/schema/books.py
sanskrit_data/schema/common.py
sanskrit_data/schema/users.py
sanskrit_data/schema/grammar/__init__.py
sanskrit_data/schema/grammar/sanskrit.py
sanskrit_data/schema/ullekhanam/__init__.py
sanskrit_data/schema/ullekhanam/sanskrit.py
sanskrit_data/testing/__init__.py
sanskrit_data/testing/pytest_plugin/__init__.py
tests/db/__init__.py
tests/db/db_interface_test.py
tests/schema/__init__.py
tests/schema/annotation_validation_test.py
tests/schema/common_serialization_test.py
tests/schema/common_test.py
tests/schema/json_object_node_test.py
tests/schema/ullekhanam_db_round_trip_test.py
sanskrit_data-0.8.14.dist-info/LICENSE.txt
sanskrit_data-0.8.14.dist-info/METADATA
sanskrit_data-0.8.14.dist-info/WHEEL
sanskrit_data-0.8.14.dist-info/entry_points.txt
sanskrit_data-0.8.14.dist-info/top_level.txt
sanskrit_data-0.8.14.dist-info/RECORD
